Workbook
Name покупатели: #REF!
Name Срез_Годы__Дата: #N/A
Name Срез_Годы__Дата1: #N/A
Name Срез_Годы__Дата2: #N/A
Name Срез_Годы__Дата3: #N/A
Name Срез_Кварталы__Дата: #N/A
Name Срез_Кварталы__Дата1: #N/A
Name Срез_магазин: #N/A
Name Срез_магазин1: #N/A
Name Срез_магазин2: #N/A
Name Срез_магазин3: #N/A
Name Срез_Месяцы__Дата: #N/A
Name Срез_Товар: #N/A
Name Срез_Товар1: #N/A

Sheet  КР задание
B1: В отдельных файлах приведены данные о работе магазинов игрушек
B3: Выбрать номер варианта в соответствие с номером по списку, выделить эту строку желтым в таблице.
B4: Скачать файл в свою папку, дав имя
B5: Имя файла : "Фамилия группа вариант" | C5: ПРИМЕР: Кошкин ФФ22-1 вариант 8
B7: Собрать все данные из папки Игрушки в этот файл с помощью Power Query. Вычислить необходимые по заданию показатели, если надо. | D7: Если данные собраны неправильно, дальнейшая проверка не производится
B8: Построить 2 информационные панели, отражающие деятельность магазинов.
B9: Состав панели определяется вариантом. Можно добавлять свои элементы. | D9: Все финансовые данные должны быть указаны с точностью до 1 рубля
D10: Все количественные данные должны быть указаны с точностью до 1 штуки
B11: Одна панель строится с использованием Excel | D11: Все процентные показатели должны быть указаны с точностью до 0,01%
B14: Аналогичная панель строится в DataLens
B16: ссылку на ДБ в DataLens положить сюда : | C16: https://datalens.yandex/j15w3poobhta3
B21: Выполненную работу :
B22: положить в личную папку на диске О этот файл с выполненным в нём заданием
B23: не позже времени, предусмотренного регламентом
B25: объект | C25: Баллы
B26: сбор данных, вычисления | C26: 1
B27: срезы: наличие, правильное подключение | C27: 1
B28: графики: соблюдение правил | C28: 1
B29: 1 KPI, 2 KPI, контрольный вопрос | C29: 1
B30: компоновка Дашборда, дизайн | C30: 1
C31: 5

Sheet вариант-номер по списку
A1: № по списку | B1: 1 обязательный график - динамика | C1: 2 обязательный график - рейтинг | D1: 3 обязательный график - доля | E1: 4 обязательный график для Excel | F1: 4 обязательный график для DataLensl | G1: 1 KPI | H1: 2 KPI для Excel | I1: 2 для DataLensl Вкладка с таблицей | J1: контрольный вопрос
A2: 3 | B2: динамика продаж (выручка) | C2: магазинов по количеству продаж | D2: менеджеров в общей выручке | E2: ТОП-5 товаров по числу продаж | F2: структура числа продаж магазинов по менеджерам | G2: общая выручка, число продаж, средний чек сделки | H2: лучший товар по выручке с указанием названия, выручки и плана | I2: магазины, менеджеры, товары по выручке, числу продаж, среднему чеку | J2: Какова доля выручки магазина Детский мир в 2020 году по товату Домик для кукол ?
L3: 3.1 Определите на какую сумму в заданный отчетный период был продан указанный в задании товар
L4: 3.2 Определите, какую долю эта сумма составляет от общего объема выручки за этот период
L5: 3.3 Выведите фамилию менеджера, получившего за этот период наибольшую выручку от продажи указанного товара и эту сумму через срез.

Sheet прайс
B2: Товар | C2: Цена за шт., руб
B3: Медведь рыжий | C3: 3100
B4: Медведь белый | C4: 2200
B5: Медведь мягкий | C5: 2560
B6: Мозаика | C6: 680
B7: Кукла Маша | C7: 1788
B8: Кукла Даша | C8: 2450
B9: Кукла Аленка | C9: 4500
B10: Конструктор малый | C10: 1600
B11: Конструктор большой | C11: 3796
B12: Конструктор строительный | C12: 4455
B13: Домик для куклы сборный | C13: 2000
B14: Домик для куклы с мебелью | C14: 5789
B15: Домик для куклы розовый | C15: 3470

Sheet Итоговая
A1: Дата | B1: Товар | C1: количество_единиц_товара | D1: выручка | E1: менеджер | F1: магазин | G1: Товар | H1: Цена_за_шт.,_руб | J1: Сумма_по_полю_выручка | K1: Названия столбцов
A2: 42382.22 | B2: Мозаика | C2: 13 | D2: =VLOOKUP(Добавить1[[#This Row],[Товар]],$G$1:$H$14,2,0)*Добавить1[[#This Row],[количество_единиц_товара]] -> 8840 | E2: Иванисов Максим | F2: Детки-конфетки | G2: Медведь рыжий | H2: 3100 | J2: Названия_строк | K2: Детки-конфетки | L2: Детский_мир | M2: Машенька | N2: Мир_детства | O2: Общий_итог
A3: 42392.014 | B3: Конструктор строительный | C3: 14 | D3: =VLOOKUP(Добавить1[[#This Row],[Товар]],$G$1:$H$14,2,0)*Добавить1[[#This Row],[количество_единиц_товара]] -> 62370 | E3: Немченко Дарья | F3: Детки-конфетки | G3: Медведь белый | H3: 2200 | J3: 2016 | K3: 3058599 | L3: 2373098 | M3: 2244450 | N3: 2373303 | O3: 10049450
A4: 42394.635 | B4: Медведь мягкий | C4: 38 | D4: =VLOOKUP(Добавить1[[#This Row],[Товар]],$G$1:$H$14,2,0)*Добавить1[[#This Row],[количество_единиц_товара]] -> 97280 | E4: Иванисов Максим | F4: Детки-конфетки | G4: Медведь мягкий | H4: 2560 | J4: 2017 | K4: 2936869 | L4: 2571584 | M4: 2423035 | N4: 2329470 | O4: 10260958
A5: 42396.053 | B5: Конструктор строительный | C5: 35 | D5: =VLOOKUP(Добавить1[[#This Row],[Товар]],$G$1:$H$14,2,0)*Добавить1[[#This Row],[количество_единиц_товара]] -> 155925 | E5: Иванисов Максим | F5: Детки-конфетки | G5: Мозаика | H5: 680 | J5: 2018 | K5: 2156012 | L5: 2656881 | M5: 2553694 | N5: 2481183 | O5: 9847770
A6: 42403.714 | B6: Кукла Маша | C6: 29 | D6: =VLOOKUP(Добавить1[[#This Row],[Товар]],$G$1:$H$14,2,0)*Добавить1[[#This Row],[количество_единиц_товара]] -> 51852 | E6: Загорский Глеб | F6: Детки-конфетки | G6: Кукла Маша | H6: 1788 | J6: 2019 | K6: 2513033 | L6: 1990374 | M6: 2680357 | N6: 2030807 | O6: 9214571
A7: 42407.948 | B7: Медведь мягкий | C7: 26 | D7: =VLOOKUP(Добавить1[[#This Row],[Товар]],$G$1:$H$14,2,0)*Добавить1[[#This Row],[количество_единиц_товара]] -> 66560 | E7: Загорский Глеб | F7: Детки-конфетки | G7: Кукла Даша | H7: 2450 | J7: 2020 | K7: 2218580 | L7: 2710371 | M7: 3387188 | N7: 2385127 | O7: 10701266
A8: 42422.93 | B8: Мозаика | C8: 23 | D8: =VLOOKUP(Добавить1[[#This Row],[Товар]],$G$1:$H$14,2,0)*Добавить1[[#This Row],[количество_единиц_товара]] -> 15640 | E8: Загорский Глеб | F8: Детки-конфетки | G8: Кукла Аленка | H8: 4500 | J8: 2021 | K8: 1542632 | L8: 1974241 | M8: 1356046 | N8: 2342699 | O8: 7215618
A9: 42430.915 | B9: Конструктор малый | C9: 22 | D9: =VLOOKUP(Добавить1[[#This Row],[Товар]],$G$1:$H$14,2,0)*Добавить1[[#This Row],[количество_единиц_товара]] -> 35200 | E9: Загорский Глеб | F9: Детки-конфетки | G9: Конструктор малый | H9: 1600 | J9: Общий_итог | K9: 14425725 | L9: 14276549 | M9: 14644770 | N9: 13942589 | O9: 57289633
A10: 42439.666 | B10: Медведь рыжий | C10: 29 | D10: =VLOOKUP(Добавить1[[#This Row],[Товар]],$G$1:$H$14,2,0)*Добавить1[[#This Row],[количество_единиц_товара]] -> 89900 | E10: Загорский Глеб | F10: Детки-конфетки | G10: Конструктор большой | H10: 3796
A11: 42467.986 | B11: Конструктор малый | C11: 10 | D11: =VLOOKUP(Добавить1[[#This Row],[Товар]],$G$1:$H$14,2,0)*Добавить1[[#This Row],[количество_единиц_товара]] -> 16000 | E11: Загорский Глеб | F11: Детки-конфетки | G11: Конструктор строительный | H11: 4455
A12: 42475.27 | B12: Мозаика | C12: 39 | D12: =VLOOKUP(Добавить1[[#This Row],[Товар]],$G$1:$H$14,2,0)*Добавить1[[#This Row],[количество_единиц_товара]] -> 26520 | E12: Загорский Глеб | F12: Детки-конфетки | G12: Домик для куклы сборный | H12: 2000
A13: 42479.66 | B13: Мозаика | C13: 22 | D13: =VLOOKUP(Добавить1[[#This Row],[Товар]],$G$1:$H$14,2,0)*Добавить1[[#This Row],[количество_единиц_товара]] -> 14960 | E13: Загорский Глеб | F13: Детки-конфетки | G13: Домик для куклы с мебелью | H13: 5789
A14: 42480.697 | B14: Домик для куклы сборный | C14: 14 | D14: =VLOOKUP(Добавить1[[#This Row],[Товар]],$G$1:$H$14,2,0)*Добавить1[[#This Row],[количество_единиц_товара]] -> 28000 | E14: Иванисов Максим | F14: Детки-конфетки | G14: Домик для куклы розовый | H14: 3470
A15: 42483.325 | B15: Кукла Даша | C15: 28 | D15: =VLOOKUP(Добавить1[[#This Row],[Товар]],$G$1:$H$14,2,0)*Добавить1[[#This Row],[количество_единиц_товара]] -> 68600 | E15: Немченко Дарья | F15: Детки-конфетки
A16: 42495.657 | B16: Медведь рыжий | C16: 22 | D16: =VLOOKUP(Добавить1[[#This Row],[Товар]],$G$1:$H$14,2,0)*Добавить1[[#This Row],[количество_единиц_товара]] -> 68200 | E16: Иванисов Максим | F16: Детки-конфетки
A17: 42513.539 | B17: Медведь белый | C17: 22 | D17: =VLOOKUP(Добавить1[[#This Row],[Товар]],$G$1:$H$14,2,0)*Добавить1[[#This Row],[количество_единиц_товара]] -> 48400 | E17: Иванисов Максим | F17: Детки-конфетки
A18: 42524.252 | B18: Медведь рыжий | C18: 39 | D18: =VLOOKUP(Добавить1[[#This Row],[Товар]],$G$1:$H$14,2,0)*Добавить1[[#This Row],[количество_единиц_товара]] -> 120900 | E18: Немченко Дарья | F18: Детки-конфетки
A19: 42532.015 | B19: Домик для куклы розовый | C19: 12 | D19: =VLOOKUP(Добавить1[[#This Row],[Товар]],$G$1:$H$14,2,0)*Добавить1[[#This Row],[количество_единиц_товара]] -> 41640 | E19: Иванисов Максим | F19: Детки-конфетки
A20: 42536.244 | B20: Медведь мягкий | C20: 16 | D20: =VLOOKUP(Добавить1[[#This Row],[Товар]],$G$1:$H$14,2,0)*Добавить1[[#This Row],[количество_единиц_товара]] -> 40960 | E20: Иванисов Максим | F20: Детки-конфетки
A21: 42540.788 | B21: Конструктор строительный | C21: 37 | D21: =VLOOKUP(Добавить1[[#This Row],[Товар]],$G$1:$H$14,2,0)*Добавить1[[#This Row],[количество_единиц_товара]] -> 164835 | E21: Немченко Дарья | F21: Детки-конфетки
A22: 42551.354 | B22: Кукла Даша | C22: 27 | D22: =VLOOKUP(Добавить1[[#This Row],[Товар]],$G$1:$H$14,2,0)*Добавить1[[#This Row],[количество_единиц_товара]] -> 66150 | E22: Иванисов Максим | F22: Детки-конфетки
A23: 42558.12 | B23: Домик для куклы с мебелью | C23: 36 | D23: =VLOOKUP(Добавить1[[#This Row],[Товар]],$G$1:$H$14,2,0)*Добавить1[[#This Row],[количество_единиц_товара]] -> 208404 | E23: Иванисов Максим | F23: Детки-конфетки
A24: 42558.87 | B24: Кукла Даша | C24: 37 | D24: =VLOOKUP(Добавить1[[#This Row],[Товар]],$G$1:$H$14,2,0)*Добавить1[[#This Row],[количество_единиц_товара]] -> 90650 | E24: Немченко Дарья | F24: Детки-конфетки
A25: 42567.749 | B25: Домик для куклы с мебелью | C25: 17 | D25: =VLOOKUP(Добавить1[[#This Row],[Товар]],$G$1:$H$14,2,0)*Добавить1[[#This Row],[количество_единиц_товара]] -> 98413 | E25: Иванисов Максим | F25: Детки-конфетки
A26: 42582.422 | B26: Домик для куклы сборный | C26: 39 | D26: =VLOOKUP(Добавить1[[#This Row],[Товар]],$G$1:$H$14,2,0)*Добавить1[[#This Row],[количество_единиц_товара]] -> 78000 | E26: Иванисов Максим | F26: Детки-конфетки
... A51: 42815.676 | B51: Конструктор строительный | C51: 12 | D51: =VLOOKUP(Добавить1[[#This Row],[Товар]],$G$1:$H$14,2,0)*Добавить1[[#This Row],[количество_единиц_товара]] -> 53460 | E51: Загорский Глеб | F51: Детки-конфетки
A52: 42816.997 | B52: Медведь мягкий | C52: 15 | D52: =VLOOKUP(Добавить1[[#This Row],[Товар]],$G$1:$H$14,2,0)*Добавить1[[#This Row],[количество_единиц_товара]] -> 38400 | E52: Иванисов Максим | F52: Детки-конфетки | N52: Названия строк | O52: Сумма по полю количество единиц товара
A53: 42817.949 | B53: Медведь рыжий | C53: 17 | D53: =VLOOKUP(Добавить1[[#This Row],[Товар]],$G$1:$H$14,2,0)*Добавить1[[#This Row],[количество_единиц_товара]] -> 52700 | E53: Немченко Дарья | F53: Детки-конфетки | N53: Мир детства | O53: 5377
A54: 42827.337 | B54: Домик для куклы с мебелью | C54: 23 | D54: =VLOOKUP(Добавить1[[#This Row],[Товар]],$G$1:$H$14,2,0)*Добавить1[[#This Row],[количество_единиц_товара]] -> 133147 | E54: Немченко Дарья | F54: Детки-конфетки | N54: Детский мир | O54: 5497
A55: 42830.805 | B55: Кукла Аленка | C55: 37 | D55: =VLOOKUP(Добавить1[[#This Row],[Товар]],$G$1:$H$14,2,0)*Добавить1[[#This Row],[количество_единиц_товара]] -> 166500 | E55: Немченко Дарья | F55: Детки-конфетки | N55: Детки-конфетки | O55: 5528
A56: 42833.667 | B56: Медведь белый | C56: 33 | D56: =VLOOKUP(Добавить1[[#This Row],[Товар]],$G$1:$H$14,2,0)*Добавить1[[#This Row],[количество_единиц_товара]] -> 72600 | E56: Немченко Дарья | F56: Детки-конфетки | N56: Машенька | O56: 5588
A57: 42838.313 | B57: Медведь рыжий | C57: 23 | D57: =VLOOKUP(Добавить1[[#This Row],[Товар]],$G$1:$H$14,2,0)*Добавить1[[#This Row],[количество_единиц_товара]] -> 71300 | E57: Немченко Дарья | F57: Детки-конфетки | N57: Общий итог | O57: 21990
A58: 42841.78 | B58: Кукла Даша | C58: 23 | D58: =VLOOKUP(Добавить1[[#This Row],[Товар]],$G$1:$H$14,2,0)*Добавить1[[#This Row],[количество_единиц_товара]] -> 56350 | E58: Немченко Дарья | F58: Детки-конфетки
A59: 42845.75 | B59: Медведь мягкий | C59: 11 | D59: =VLOOKUP(Добавить1[[#This Row],[Товар]],$G$1:$H$14,2,0)*Добавить1[[#This Row],[количество_единиц_товара]] -> 28160 | E59: Немченко Дарья | F59: Детки-конфетки
A60: 42846.468 | B60: Медведь рыжий | C60: 11 | D60: =VLOOKUP(Добавить1[[#This Row],[Товар]],$G$1:$H$14,2,0)*Добавить1[[#This Row],[количество_единиц_товара]] -> 34100 | E60: Немченко Дарья | F60: Детки-конфетки
A61: 42865.513 | B61: Домик для куклы сборный | C61: 37 | D61: =VLOOKUP(Добавить1[[#This Row],[Товар]],$G$1:$H$14,2,0)*Добавить1[[#This Row],[количество_единиц_товара]] -> 74000 | E61: Иванисов Максим | F61: Детки-конфетки
A62: 42875.664 | B62: Конструктор строительный | C62: 22 | D62: =VLOOKUP(Добавить1[[#This Row],[Товар]],$G$1:$H$14,2,0)*Добавить1[[#This Row],[количество_единиц_товара]] -> 98010 | E62: Иванисов Максим | F62: Детки-конфетки
A63: 42879.179 | B63: Конструктор строительный | C63: 32 | D63: =VLOOKUP(Добавить1[[#This Row],[Товар]],$G$1:$H$14,2,0)*Добавить1[[#This Row],[количество_единиц_товара]] -> 142560 | E63: Загорский Глеб | F63: Детки-конфетки
A64: 42885.423 | B64: Медведь мягкий | C64: 39 | D64: =VLOOKUP(Добавить1[[#This Row],[Товар]],$G$1:$H$14,2,0)*Добавить1[[#This Row],[количество_единиц_товара]] -> 99840 | E64: Загорский Глеб | F64: Детки-конфетки
A65: 42892.097 | B65: Кукла Даша | C65: 13 | D65: =VLOOKUP(Добавить1[[#This Row],[Товар]],$G$1:$H$14,2,0)*Добавить1[[#This Row],[количество_единиц_товара]] -> 31850 | E65: Загорский Глеб | F65: Детки-конфетки
A66: 42894.88 | B66: Мозаика | C66: 21 | D66: =VLOOKUP(Добавить1[[#This Row],[Товар]],$G$1:$H$14,2,0)*Добавить1[[#This Row],[количество_единиц_товара]] -> 14280 | E66: Загорский Глеб | F66: Детки-конфетки
A67: 42899.297 | B67: Медведь рыжий | C67: 24 | D67: =VLOOKUP(Добавить1[[#This Row],[Товар]],$G$1:$H$14,2,0)*Добавить1[[#This Row],[количество_единиц_товара]] -> 74400 | E67: Загорский Глеб | F67: Детки-конфетки
A68: 42901.118 | B68: Кукла Маша | C68: 13 | D68: =VLOOKUP(Добавить1[[#This Row],[Товар]],$G$1:$H$14,2,0)*Добавить1[[#This Row],[количество_единиц_товара]] -> 23244 | E68: Иванисов Максим | F68: Детки-конфетки
A69: 42906.77 | B69: Кукла Аленка | C69: 26 | D69: =VLOOKUP(Добавить1[[#This Row],[Товар]],$G$1:$H$14,2,0)*Добавить1[[#This Row],[количество_единиц_товара]] -> 117000 | E69: Немченко Дарья | F69: Детки-конфетки
... A87: 43112.089 | B87: Медведь белый | C87: 12 | D87: =VLOOKUP(Добавить1[[#This Row],[Товар]],$G$1:$H$14,2,0)*Добавить1[[#This Row],[количество_единиц_товара]] -> 26400 | E87: Иванисов Максим | F87: Детки-конфетки
A88: 43117.441 | B88: Конструктор малый | C88: 36 | D88: =VLOOKUP(Добавить1[[#This Row],[Товар]],$G$1:$H$14,2,0)*Добавить1[[#This Row],[количество_единиц_товара]] -> 57600 | E88: Немченко Дарья | F88: Детки-конфетки | L88: Названия строк | M88: Сумма по полю выручка
A89: 43136.332 | B89: Конструктор строительный | C89: 22 | D89: =VLOOKUP(Добавить1[[#This Row],[Товар]],$G$1:$H$14,2,0)*Добавить1[[#This Row],[количество_единиц_товара]] -> 98010 | E89: Немченко Дарья | F89: Детки-конфетки | L89: Белоусова Валерия | M89: 0.086053929
A90: 43145.98 | B90: Мозаика | C90: 37 | D90: =VLOOKUP(Добавить1[[#This Row],[Товар]],$G$1:$H$14,2,0)*Добавить1[[#This Row],[количество_единиц_товара]] -> 25160 | E90: Немченко Дарья | F90: Детки-конфетки | L90: Жиркова Ольга | M90: 0.24008038
A91: 43146.198 | B91: Медведь рыжий | C91: 11 | D91: =VLOOKUP(Добавить1[[#This Row],[Товар]],$G$1:$H$14,2,0)*Добавить1[[#This Row],[количество_единиц_товара]] -> 34100 | E91: Немченко Дарья | F91: Детки-конфетки | L91: Загорский Глеб | M91: 0.072529126
A92: 43151.143 | B92: Медведь белый | C92: 18 | D92: =VLOOKUP(Добавить1[[#This Row],[Товар]],$G$1:$H$14,2,0)*Добавить1[[#This Row],[количество_единиц_товара]] -> 39600 | E92: Немченко Дарья | F92: Детки-конфетки | L92: Зайцев Кирилл | M92: 0.072790465
A93: 43163.993 | B93: Домик для куклы с мебелью | C93: 35 | D93: =VLOOKUP(Добавить1[[#This Row],[Товар]],$G$1:$H$14,2,0)*Добавить1[[#This Row],[количество_единиц_товара]] -> 202615 | E93: Немченко Дарья | F93: Детки-конфетки | L93: Иванисов Максим | M93: 0.085065617
A94: 43164.932 | B94: Мозаика | C94: 24 | D94: =VLOOKUP(Добавить1[[#This Row],[Товар]],$G$1:$H$14,2,0)*Добавить1[[#This Row],[количество_единиц_товара]] -> 16320 | E94: Немченко Дарья | F94: Детки-конфетки | L94: Немченко Дарья | M94: 0.094208668
A95: 43179.439 | B95: Медведь рыжий | C95: 18 | D95: =VLOOKUP(Добавить1[[#This Row],[Товар]],$G$1:$H$14,2,0)*Добавить1[[#This Row],[количество_единиц_товара]] -> 55800 | E95: Немченко Дарья | F95: Детки-конфетки | L95: Родинов Илья | M95: 0.21098852
A96: 43183.586 | B96: Мозаика | C96: 15 | D96: =VLOOKUP(Добавить1[[#This Row],[Товар]],$G$1:$H$14,2,0)*Добавить1[[#This Row],[количество_единиц_товара]] -> 10200 | E96: Немченко Дарья | F96: Детки-конфетки | L96: Ткачева Наталья | M96: 0.084525799
A97: 43187.752 | B97: Конструктор малый | C97: 30 | D97: =VLOOKUP(Добавить1[[#This Row],[Товар]],$G$1:$H$14,2,0)*Добавить1[[#This Row],[количество_единиц_товара]] -> 48000 | E97: Немченко Дарья | F97: Детки-конфетки | L97: Усачев Михаил | M97: 0.053757492
A98: 43195.099 | B98: Конструктор строительный | C98: 26 | D98: =VLOOKUP(Добавить1[[#This Row],[Товар]],$G$1:$H$14,2,0)*Добавить1[[#This Row],[количество_единиц_товара]] -> 115830 | E98: Загорский Глеб | F98: Детки-конфетки | L98: Общий итог | M98: 1
A99: 43203.417 | B99: Мозаика | C99: 24 | D99: =VLOOKUP(Добавить1[[#This Row],[Товар]],$G$1:$H$14,2,0)*Добавить1[[#This Row],[количество_единиц_товара]] -> 16320 | E99: Загорский Глеб | F99: Детки-конфетки
A100: 43219.541 | B100: Медведь мягкий | C100: 31 | D100: =VLOOKUP(Добавить1[[#This Row],[Товар]],$G$1:$H$14,2,0)*Добавить1[[#This Row],[количество_единиц_товара]] -> 79360 | E100: Загорский Глеб | F100: Детки-конфетки
A101: 43230.485 | B101: Домик для куклы сборный | C101: 16 | D101: =VLOOKUP(Добавить1[[#This Row],[Товар]],$G$1:$H$14,2,0)*Добавить1[[#This Row],[количество_единиц_товара]] -> 32000 | E101: Загорский Глеб | F101: Детки-конфетки
A102: 43234.866 | B102: Кукла Маша | C102: 35 | D102: =VLOOKUP(Добавить1[[#This Row],[Товар]],$G$1:$H$14,2,0)*Добавить1[[#This Row],[количество_единиц_товара]] -> 62580 | E102: Иванисов Максим | F102: Детки-конфетки
A103: 43237.361 | B103: Медведь мягкий | C103: 17 | D103: =VLOOKUP(Добавить1[[#This Row],[Товар]],$G$1:$H$14,2,0)*Добавить1[[#This Row],[количество_единиц_товара]] -> 43520 | E103: Немченко Дарья | F103: Детки-конфетки
A104: 43249.825 | B104: Домик для куклы с мебелью | C104: 30 | D104: =VLOOKUP(Добавить1[[#This Row],[Товар]],$G$1:$H$14,2,0)*Добавить1[[#This Row],[количество_единиц_товара]] -> 173670 | E104: Немченко Дарья | F104: Детки-конфетки
A105: 43250.833 | B105: Медведь белый | C105: 17 | D105: =VLOOKUP(Добавить1[[#This Row],[Товар]],$G$1:$H$14,2,0)*Добавить1[[#This Row],[количество_единиц_товара]] -> 37400 | E105: Иванисов Максим | F105: Детки-конфетки
A106: 43259.91 | B106: Кукла Даша | C106: 34 | D106: =VLOOKUP(Добавить1[[#This Row],[Товар]],$G$1:$H$14,2,0)*Добавить1[[#This Row],[количество_единиц_товара]] -> 83300 | E106: Немченко Дарья | F106: Детки-конфетки
A107: 43284.146 | B107: Кукла Маша | C107: 24 | D107: =VLOOKUP(Добавить1[[#This Row],[Товар]],$G$1:$H$14,2,0)*Добавить1[[#This Row],[количество_единиц_товара]] -> 42912 | E107: Немченко Дарья | F107: Детки-конфетки
A108: 43284.689 | B108: Домик для куклы сборный | C108: 16 | D108: =VLOOKUP(Добавить1[[#This Row],[Товар]],$G$1:$H$14,2,0)*Добавить1[[#This Row],[количество_единиц_товара]] -> 32000 | E108: Иванисов Максим | F108: Детки-конфетки
A109: 43287.522 | B109: Мозаика | C109: 14 | D109: =VLOOKUP(Добавить1[[#This Row],[Товар]],$G$1:$H$14,2,0)*Добавить1[[#This Row],[количество_единиц_товара]] -> 9520 | E109: Немченко Дарья | F109: Детки-конфетки
A110: 43287.86 | B110: Домик для куклы с мебелью | C110: 27 | D110: =VLOOKUP(Добавить1[[#This Row],[Товар]],$G$1:$H$14,2,0)*Добавить1[[#This Row],[количество_единиц_товара]] -> 156303 | E110: Немченко Дарья | F110: Детки-конфетки
... A123: 43408.261 | B123: Медведь мягкий | C123: 17 | D123: =VLOOKUP(Добавить1[[#This Row],[Товар]],$G$1:$H$14,2,0)*Добавить1[[#This Row],[количество_единиц_товара]] -> 43520 | E123: Иванисов Максим | F123: Детки-конфетки
A124: 43432.191 | B124: Конструктор малый | C124: 22 | D124: =VLOOKUP(Добавить1[[#This Row],[Товар]],$G$1:$H$14,2,0)*Добавить1[[#This Row],[количество_единиц_товара]] -> 35200 | E124: Немченко Дарья | F124: Детки-конфетки | L124: Названия строк | M124: Сумма по полю количество единиц товара
A125: 43437.237 | B125: Домик для куклы сборный | C125: 26 | D125: =VLOOKUP(Добавить1[[#This Row],[Товар]],$G$1:$H$14,2,0)*Добавить1[[#This Row],[количество_единиц_товара]] -> 52000 | E125: Иванисов Максим | F125: Детки-конфетки | L125: Кукла Даша | M125: 1823
A126: 43453.552 | B126: Медведь мягкий | C126: 21 | D126: =VLOOKUP(Добавить1[[#This Row],[Товар]],$G$1:$H$14,2,0)*Добавить1[[#This Row],[количество_единиц_товара]] -> 53760 | E126: Немченко Дарья | F126: Детки-конфетки | L126: Конструктор строительный | M126: 2115
A127: 43453.882 | B127: Домик для куклы сборный | C127: 28 | D127: =VLOOKUP(Добавить1[[#This Row],[Товар]],$G$1:$H$14,2,0)*Добавить1[[#This Row],[количество_единиц_товара]] -> 56000 | E127: Иванисов Максим | F127: Детки-конфетки | L127: Медведь мягкий | M127: 2425
A128: 43461.675 | B128: Мозаика | C128: 18 | D128: =VLOOKUP(Добавить1[[#This Row],[Товар]],$G$1:$H$14,2,0)*Добавить1[[#This Row],[количество_единиц_товара]] -> 12240 | E128: Немченко Дарья | F128: Детки-конфетки | L128: Домик для куклы сборный | M128: 2556
A129: 43474.41 | B129: Домик для куклы сборный | C129: 14 | D129: =VLOOKUP(Добавить1[[#This Row],[Товар]],$G$1:$H$14,2,0)*Добавить1[[#This Row],[количество_единиц_товара]] -> 28000 | E129: Иванисов Максим | F129: Детки-конфетки | L129: Мозаика | M129: 3520
A130: 43484.299 | B130: Конструктор малый | C130: 13 | D130: =VLOOKUP(Добавить1[[#This Row],[Товар]],$G$1:$H$14,2,0)*Добавить1[[#This Row],[количество_единиц_товара]] -> 20800 | E130: Немченко Дарья | F130: Детки-конфетки | L130: Общий итог | M130: 12439
A131: 43488.168 | B131: Домик для куклы розовый | C131: 26 | D131: =VLOOKUP(Добавить1[[#This Row],[Товар]],$G$1:$H$14,2,0)*Добавить1[[#This Row],[количество_единиц_товара]] -> 90220 | E131: Иванисов Максим | F131: Детки-конфетки
A132: 43492.683 | B132: Конструктор малый | C132: 29 | D132: =VLOOKUP(Добавить1[[#This Row],[Товар]],$G$1:$H$14,2,0)*Добавить1[[#This Row],[количество_единиц_товара]] -> 46400 | E132: Иванисов Максим | F132: Детки-конфетки
A133: 43511.449 | B133: Медведь мягкий | C133: 23 | D133: =VLOOKUP(Добавить1[[#This Row],[Товар]],$G$1:$H$14,2,0)*Добавить1[[#This Row],[количество_единиц_товара]] -> 58880 | E133: Иванисов Максим | F133: Детки-конфетки
A134: 43514.363 | B134: Мозаика | C134: 14 | D134: =VLOOKUP(Добавить1[[#This Row],[Товар]],$G$1:$H$14,2,0)*Добавить1[[#This Row],[количество_единиц_товара]] -> 9520 | E134: Иванисов Максим | F134: Детки-конфетки
A135: 43531.12 | B135: Конструктор строительный | C135: 23 | D135: =VLOOKUP(Добавить1[[#This Row],[Товар]],$G$1:$H$14,2,0)*Добавить1[[#This Row],[количество_единиц_товара]] -> 102465 | E135: Иванисов Максим | F135: Детки-конфетки
A136: 43541.803 | B136: Медведь рыжий | C136: 16 | D136: =VLOOKUP(Добавить1[[#This Row],[Товар]],$G$1:$H$14,2,0)*Добавить1[[#This Row],[количество_единиц_товара]] -> 49600 | E136: Иванисов Максим | F136: Детки-конфетки
A137: 43551.832 | B137: Мозаика | C137: 10 | D137: =VLOOKUP(Добавить1[[#This Row],[Товар]],$G$1:$H$14,2,0)*Добавить1[[#This Row],[количество_единиц_товара]] -> 6800 | E137: Иванисов Максим | F137: Детки-конфетки
A138: 43554.148 | B138: Кукла Даша | C138: 22 | D138: =VLOOKUP(Добавить1[[#This Row],[Товар]],$G$1:$H$14,2,0)*Добавить1[[#This Row],[количество_единиц_товара]] -> 53900 | E138: Иванисов Максим | F138: Детки-конфетки
A139: 43560.304 | B139: Конструктор строительный | C139: 33 | D139: =VLOOKUP(Добавить1[[#This Row],[Товар]],$G$1:$H$14,2,0)*Добавить1[[#This Row],[количество_единиц_товара]] -> 147015 | E139: Иванисов Максим | F139: Детки-конфетки
A140: 43565.933 | B140: Медведь белый | C140: 24 | D140: =VLOOKUP(Добавить1[[#This Row],[Товар]],$G$1:$H$14,2,0)*Добавить1[[#This Row],[количество_единиц_товара]] -> 52800 | E140: Иванисов Максим | F140: Детки-конфетки
A141: 43568.254 | B141: Медведь мягкий | C141: 34 | D141: =VLOOKUP(Добавить1[[#This Row],[Товар]],$G$1:$H$14,2,0)*Добавить1[[#This Row],[количество_единиц_товара]] -> 87040 | E141: Загорский Глеб | F141: Детки-конфетки
A142: 43583.9 | B142: Медведь белый | C142: 33 | D142: =VLOOKUP(Добавить1[[#This Row],[Товар]],$G$1:$H$14,2,0)*Добавить1[[#This Row],[количество_единиц_товара]] -> 72600 | E142: Немченко Дарья | F142: Детки-конфетки
... A157: 43725.095 | B157: Домик для куклы сборный | C157: 17 | D157: =VLOOKUP(Добавить1[[#This Row],[Товар]],$G$1:$H$14,2,0)*Добавить1[[#This Row],[количество_единиц_товара]] -> 34000 | E157: Иванисов Максим | F157: Детки-конфетки
A158: 43725.546 | B158: Медведь белый | C158: 36 | D158: =VLOOKUP(Добавить1[[#This Row],[Товар]],$G$1:$H$14,2,0)*Добавить1[[#This Row],[количество_единиц_товара]] -> 79200 | E158: Немченко Дарья | F158: Детки-конфетки | H158: Названия строк | I158: Сумма по полю выручка | J158: план по конструктору | K158: выполнение плана
A159: 43729.509 | B159: Домик для куклы с мебелью | C159: 30 | D159: =VLOOKUP(Добавить1[[#This Row],[Товар]],$G$1:$H$14,2,0)*Добавить1[[#This Row],[количество_единиц_товара]] -> 173670 | E159: Иванисов Максим | F159: Детки-конфетки | H159: Конструктор строительный | I159: 9422325 | J159: =GETPIVOTDATA("выручка",$H$158,"Товар","Конструктор строительный")*1.15 -> 10835674 | K159: =GETPIVOTDATA("выручка",$H$158,"Товар","Конструктор строительный")/J159 -> 0.86956522
A160: 43742.813 | B160: Конструктор строительный | C160: 28 | D160: =VLOOKUP(Добавить1[[#This Row],[Товар]],$G$1:$H$14,2,0)*Добавить1[[#This Row],[количество_единиц_товара]] -> 124740 | E160: Иванисов Максим | F160: Детки-конфетки | H160: Домик для куклы с мебелью | I160: 7004690
A161: 43748.723 | B161: Домик для куклы с мебелью | C161: 33 | D161: =VLOOKUP(Добавить1[[#This Row],[Товар]],$G$1:$H$14,2,0)*Добавить1[[#This Row],[количество_единиц_товара]] -> 191037 | E161: Немченко Дарья | F161: Детки-конфетки | H161: Медведь мягкий | I161: 6208000
A162: 43752.35 | B162: Конструктор малый | C162: 37 | D162: =VLOOKUP(Добавить1[[#This Row],[Товар]],$G$1:$H$14,2,0)*Добавить1[[#This Row],[количество_единиц_товара]] -> 59200 | E162: Иванисов Максим | F162: Детки-конфетки | H162: Домик для куклы сборный | I162: 5112000
A163: 43776.557 | B163: Домик для куклы розовый | C163: 27 | D163: =VLOOKUP(Добавить1[[#This Row],[Товар]],$G$1:$H$14,2,0)*Добавить1[[#This Row],[количество_единиц_товара]] -> 93690 | E163: Иванисов Максим | F163: Детки-конфетки | H163: Медведь рыжий | I163: 4808100
A164: 43810.121 | B164: Медведь рыжий | C164: 16 | D164: =VLOOKUP(Добавить1[[#This Row],[Товар]],$G$1:$H$14,2,0)*Добавить1[[#This Row],[количество_единиц_товара]] -> 49600 | E164: Немченко Дарья | F164: Детки-конфетки | H164: Кукла Даша | I164: 4466350
A165: 43819.094 | B165: Мозаика | C165: 25 | D165: =VLOOKUP(Добавить1[[#This Row],[Товар]],$G$1:$H$14,2,0)*Добавить1[[#This Row],[количество_единиц_товара]] -> 17000 | E165: Иванисов Максим | F165: Детки-конфетки | H165: Кукла Аленка | I165: 4414500
A166: 43822.028 | B166: Конструктор малый | C166: 22 | D166: =VLOOKUP(Добавить1[[#This Row],[Товар]],$G$1:$H$14,2,0)*Добавить1[[#This Row],[количество_единиц_товара]] -> 35200 | E166: Иванисов Максим | F166: Детки-конфетки | H166: Домик для куклы розовый | I166: 3997440
A167: 43833.027 | B167: Домик для куклы розовый | C167: 12 | D167: =VLOOKUP(Добавить1[[#This Row],[Товар]],$G$1:$H$14,2,0)*Добавить1[[#This Row],[количество_единиц_товара]] -> 41640 | E167: Немченко Дарья | F167: Детки-конфетки | H167: Медведь белый | I167: 3641000
...

Sheet Лист1
A1: Дата | B1: Товар | C1: количество_единиц_товара | D1: выручка | E1: менеджер | F1: магазин
A2: 42382.22 | B2: Мозаика | C2: 13 | D2: =VLOOKUP(Добавить18[[#This Row],[Товар]],Итоговая!$G$1:$H$14,2,0)*Добавить18[[#This Row],[количество_единиц_товара]] -> 8840 | E2: Иванисов Максим | F2: Детки-конфетки
A3: 42392.014 | B3: Конструктор строительный | C3: 14 | D3: =VLOOKUP(Добавить18[[#This Row],[Товар]],Итоговая!$G$1:$H$14,2,0)*Добавить18[[#This Row],[количество_единиц_товара]] -> 62370 | E3: Немченко Дарья | F3: Детки-конфетки
A4: 42394.635 | B4: Медведь мягкий | C4: 38 | D4: =VLOOKUP(Добавить18[[#This Row],[Товар]],Итоговая!$G$1:$H$14,2,0)*Добавить18[[#This Row],[количество_единиц_товара]] -> 97280 | E4: Иванисов Максим | F4: Детки-конфетки
A5: 42396.053 | B5: Конструктор строительный | C5: 35 | D5: =VLOOKUP(Добавить18[[#This Row],[Товар]],Итоговая!$G$1:$H$14,2,0)*Добавить18[[#This Row],[количество_единиц_товара]] -> 155925 | E5: Иванисов Максим | F5: Детки-конфетки
A6: 42403.714 | B6: Кукла Маша | C6: 29 | D6: =VLOOKUP(Добавить18[[#This Row],[Товар]],Итоговая!$G$1:$H$14,2,0)*Добавить18[[#This Row],[количество_единиц_товара]] -> 51852 | E6: Загорский Глеб | F6: Детки-конфетки
A7: 42407.948 | B7: Медведь мягкий | C7: 26 | D7: =VLOOKUP(Добавить18[[#This Row],[Товар]],Итоговая!$G$1:$H$14,2,0)*Добавить18[[#This Row],[количество_единиц_товара]] -> 66560 | E7: Загорский Глеб | F7: Детки-конфетки
A8: 42422.93 | B8: Мозаика | C8: 23 | D8: =VLOOKUP(Добавить18[[#This Row],[Товар]],Итоговая!$G$1:$H$14,2,0)*Добавить18[[#This Row],[количество_единиц_товара]] -> 15640 | E8: Загорский Глеб | F8: Детки-конфетки
A9: 42430.915 | B9: Конструктор малый | C9: 22 | D9: =VLOOKUP(Добавить18[[#This Row],[Товар]],Итоговая!$G$1:$H$14,2,0)*Добавить18[[#This Row],[количество_единиц_товара]] -> 35200 | E9: Загорский Глеб | F9: Детки-конфетки
A10: 42439.666 | B10: Медведь рыжий | C10: 29 | D10: =VLOOKUP(Добавить18[[#This Row],[Товар]],Итоговая!$G$1:$H$14,2,0)*Добавить18[[#This Row],[количество_единиц_товара]] -> 89900 | E10: Загорский Глеб | F10: Детки-конфетки
A11: 42467.986 | B11: Конструктор малый | C11: 10 | D11: =VLOOKUP(Добавить18[[#This Row],[Товар]],Итоговая!$G$1:$H$14,2,0)*Добавить18[[#This Row],[количество_единиц_товара]] -> 16000 | E11: Загорский Глеб | F11: Детки-конфетки
A12: 42475.27 | B12: Мозаика | C12: 39 | D12: =VLOOKUP(Добавить18[[#This Row],[Товар]],Итоговая!$G$1:$H$14,2,0)*Добавить18[[#This Row],[количество_единиц_товара]] -> 26520 | E12: Загорский Глеб | F12: Детки-конфетки
A13: 42479.66 | B13: Мозаика | C13: 22 | D13: =VLOOKUP(Добавить18[[#This Row],[Товар]],Итоговая!$G$1:$H$14,2,0)*Добавить18[[#This Row],[количество_единиц_товара]] -> 14960 | E13: Загорский Глеб | F13: Детки-конфетки
... A900: 44469.988 | B900: Медведь мягкий | C900: 22 | D900: =VLOOKUP(Добавить18[[#This Row],[Товар]],Итоговая!$G$1:$H$14,2,0)*Добавить18[[#This Row],[количество_единиц_товара]] -> 56320 | E900: Зайцев Кирилл | F900: Мир детства

Sheet Детки-конфетки
A1: Дата | B1: Товар | C1: количество единиц товара | D1: выручка | E1: менеджер
A2: 42382.22 | B2: Мозаика | C2: 13 | E2: Иванисов Максим
A3: 42392.014 | B3: Конструктор строительный | C3: 14 | E3: Немченко Дарья
A4: 42394.635 | B4: Медведь мягкий | C4: 38 | E4: Иванисов Максим
A5: 42396.053 | B5: Конструктор строительный | C5: 35 | E5: Иванисов Максим
A6: 42403.714 | B6: Кукла Маша | C6: 29 | E6: Загорский Глеб
A7: 42407.948 | B7: Медведь мягкий | C7: 26 | E7: Загорский Глеб
A8: 42422.93 | B8: Мозаика | C8: 23 | E8: Загорский Глеб
A9: 42430.915 | B9: Конструктор малый | C9: 22 | E9: Загорский Глеб
A10: 42439.666 | B10: Медведь рыжий | C10: 29 | E10: Загорский Глеб
A11: 42467.986 | B11: Конструктор малый | C11: 10 | E11: Загорский Глеб
A12: 42475.27 | B12: Мозаика | C12: 39 | E12: Загорский Глеб
A13: 42479.66 | B13: Мозаика | C13: 22 | E13: Загорский Глеб
... A224: 44449.897 | B224: Домик для куклы розовый | C224: 30 | E224: Загорский Глеб

Sheet Детский мир
A1: Дата | B1: Товар | C1: количество единиц товара | D1: выручка | E1: менеджер
A2: 42385.033 | B2: Конструктор малый | C2: 35 | E2: Родинов Илья
A3: 42395.552 | B3: Медведь мягкий | C3: 10 | E3: Жиркова Ольга
A4: 42398.774 | B4: Домик для куклы сборный | C4: 30 | E4: Усачев Михаил
A5: 42405.455 | B5: Мозаика | C5: 11 | E5: Жиркова Ольга
A6: 42408.954 | B6: Медведь мягкий | C6: 31 | E6: Родинов Илья
A7: 42412.763 | B7: Мозаика | C7: 32 | E7: Усачев Михаил
A8: 42426.187 | B8: Мозаика | C8: 36 | E8: Жиркова Ольга
A9: 42440.23 | B9: Медведь рыжий | C9: 18 | E9: Усачев Михаил
A10: 42451.972 | B10: Медведь белый | C10: 37 | E10: Усачев Михаил
A11: 42464.156 | B11: Кукла Маша | C11: 40 | E11: Родинов Илья
A12: 42467.112 | B12: Домик для куклы сборный | C12: 14 | E12: Жиркова Ольга
A13: 42482.85 | B13: Конструктор малый | C13: 24 | E13: Родинов Илья
... A232: 44428.354 | B232: Кукла Даша | C232: 22 | E232: Жиркова Ольга

Sheet Машенька
A1: Дата | B1: Товар | C1: количество единиц | D1: выручка | E1: менеджер | F1: Column6 | G1: Column7 | H1: Column8 | I1: Column9 | J1: Column10 | K1: Column11
A2: 42404.649 | B2: Кукла Даша | C2: 14 | E2: Жиркова Ольга
A3: 42413.08 | B3: Домик для куклы розовый | C3: 19 | E3: Родинов Илья
A4: 42417.574 | B4: Конструктор строительный | C4: 26 | E4: Родинов Илья
A5: 42418.724 | B5: Мозаика | C5: 26 | E5: Родинов Илья
A6: 42429.497 | B6: Мозаика | C6: 25 | E6: Родинов Илья
A7: 42438.528 | B7: Мозаика | C7: 24 | E7: Родинов Илья
A8: 42444.703 | B8: Домик для куклы сборный | C8: 17 | E8: Родинов Илья
A9: 42449.184 | B9: Мозаика | C9: 21 | E9: Родинов Илья
A10: 42457.657 | B10: Мозаика | C10: 29 | E10: Родинов Илья
A11: 42460.788 | B11: Домик для куклы сборный | C11: 23 | E11: Родинов Илья
A12: 42462.718 | B12: Мозаика | C12: 14 | E12: Родинов Илья
A13: 42472.484 | B13: Конструктор малый | C13: 22 | E13: Родинов Илья
... A226: 44436.089 | B226: Медведь белый | C226: 11 | E226: Жиркова Ольга

Sheet Мир детства
A1: Дата | B1: Товар | C1: количество единиц товара | D1: выручка | E1: менеджер
A2: 42386.497 | B2: Домик для куклы сборный | C2: 25 | E2: Зайцев Кирилл
A3: 42389.494 | B3: Кукла Маша | C3: 11 | E3: Белоусова Валерия
A4: 42390.648 | B4: Медведь мягкий | C4: 18 | E4: Ткачева Наталья
A5: 42400.337 | B5: Медведь белый | C5: 38 | E5: Белоусова Валерия
A6: 42423.845 | B6: Домик для куклы с мебелью | C6: 29 | E6: Ткачева Наталья
A7: 42435.165 | B7: Медведь мягкий | C7: 25 | E7: Белоусова Валерия
A8: 42456.288 | B8: Конструктор большой | C8: 35 | E8: Белоусова Валерия
A9: 42474.675 | B9: Мозаика | C9: 30 | E9: Зайцев Кирилл
A10: 42490.471 | B10: Домик для куклы розовый | C10: 21 | E10: Белоусова Валерия
A11: 42496.198 | B11: Медведь белый | C11: 34 | E11: Зайцев Кирилл
A12: 42497.076 | B12: Конструктор строительный | C12: 20 | E12: Зайцев Кирилл
A13: 42515.363 | B13: Кукла Аленка | C13: 33 | E13: Зайцев Кирилл
... A221: 44469.988 | B221: Медведь мягкий | C221: 22 | E221: Зайцев Кирилл
